fastapi_core_services/__init__.py
fastapi_core_services/email_service.py
fastapi_core_services/plan_service.py
fastapi_core_services/stripe_service.py
rodrigo0000_fastapi_core_services-1.0.0.dist-info/METADATA
rodrigo0000_fastapi_core_services-1.0.0.dist-info/WHEEL
rodrigo0000_fastapi_core_services-1.0.0.dist-info/top_level.txt
rodrigo0000_fastapi_core_services-1.0.0.dist-info/RECORD
